{ "IoBundleList": [
    { "Type": 1, "Name": "eth0", "AssignmentGroup": "eth0-1", "PciLong": "0000:04:00.0", "Ifname": "eth0" },
    { "Type": 1, "Name": "eth1", "AssignmentGroup": "eth0-1", "PciLong": "0000:04:00.1", "Ifname": "eth1" },
    { "Type": 1, "Name": "eth2", "AssignmentGroup": "eth2", "PciLong": "0000:07:00.0", "Ifname": "eth2" },
    { "Type": 1, "Name": "eth3", "AssignmentGroup": "eth3", "PciLong": "0000:08:00.0", "Ifname": "eth3" },
    { "Type": 1, "Name": "eth4", "AssignmentGroup": "eth4-7", "PciLong": "0000:0b:00.0", "Ifname": "eth4" },
    { "Type": 1, "Name": "eth5", "AssignmentGroup": "eth4-7", "PciLong": "0000:0b:00.1", "Ifname": "eth5" },
    { "Type": 1, "Name": "eth6", "AssignmentGroup": "eth4-7", "PciLong": "0000:0b:00.2", "Ifname": "eth6" },
    { "Type": 1, "Name": "eth7", "AssignmentGroup": "eth4-7", "PciLong": "0000:0b:00.3", "Ifname": "eth7" },
    { "Type": 2, "Name": "USB0", "AssignmentGroup": "USB", "PciLong": "0000:00:14.0"},
    { "Type": 2, "Name": "USB1", "AssignmentGroup": "USB", "PciLong": "0000:00:14.0"},
    { "Type": 3, "Name": "COM1", "AssignmentGroup": "COM1", "Irq": "4", "Ioports": "3f8-3ff", "Serial": "/dev/ttyS0"},
    { "Type": 4, "Name": "Audio", "AssignmentGroup": "Audio", "PciLong": "0000:00:0e.0" }
] }
